CHANGELOG.md
LICENSE
MANIFEST.in
README.rst
setup.py
django_rq_jobs/__init__.py
django_rq_jobs/admin.py
django_rq_jobs/apps.py
django_rq_jobs/models.py
django_rq_jobs.egg-info/PKG-INFO
django_rq_jobs.egg-info/SOURCES.txt
django_rq_jobs.egg-info/dependency_links.txt
django_rq_jobs.egg-info/requires.txt
django_rq_jobs.egg-info/top_level.txt
django_rq_jobs/management/__init__.py
django_rq_jobs/management/commands/__init__.py
django_rq_jobs/management/commands/rqjobs.py
django_rq_jobs/migrations/0001_initial.py
django_rq_jobs/migrations/0002_auto_20150721_1255.py
django_rq_jobs/migrations/0003_auto_20150729_1103.py
django_rq_jobs/migrations/__init__.py
django_rq_jobs/tests/__init__.py
django_rq_jobs/tests/runtests.py
django_rq_jobs/tests/settings.py
django_rq_jobs/tests/tasks.py
django_rq_jobs/tests/tests.py
django_rq_jobs/tests/urls.py